eosapi/__init__.py
eosapi/__version__.py
eosapi/eosapi.py
eosapi/exceptions.py
eosapi/packer.py
eosapi/transaction.py
eosapi-1.0.2.dist-info/LICENSE
eosapi-1.0.2.dist-info/METADATA
eosapi-1.0.2.dist-info/WHEEL
eosapi-1.0.2.dist-info/top_level.txt
eosapi-1.0.2.dist-info/RECORD
