Metadata-Version: 2.1
Name: eosapi
Version: 1.0.2
Summary: a simple, high-level and lightweight eosio sdk write by python
Home-page: https://github.com/encoderlee/eosapi
Author: encoderlee
Author-email: encoderlee@gmail.com
License: MIT
Platform: UNKNOWN
Classifier: Programming Language :: Python :: 3
Classifier: License :: OSI Approved :: MIT License
Classifier: Operating System :: OS Independent
License-File: LICENSE
Requires-Dist: requests
Requires-Dist: cryptos
Requires-Dist: base58
